pt_checkin/__init__.py
pt_checkin/cli.py
pt_checkin/base/__init__.py
pt_checkin/base/detail.py
pt_checkin/base/message.py
pt_checkin/base/request.py
pt_checkin/base/selector_builder.py
pt_checkin/base/sign_in.py
pt_checkin/base/signin_strategy.py
pt_checkin/base/work.py
pt_checkin/core/__init__.py
pt_checkin/core/config_manager.py
pt_checkin/core/entry.py
pt_checkin/core/executor.py
pt_checkin/core/scheduler.py
pt_checkin/core/signin_status.py
pt_checkin/schema/__init__.py
pt_checkin/schema/avistaz.py
pt_checkin/schema/discuz.py
pt_checkin/schema/gazelle.py
pt_checkin/schema/luminance.py
pt_checkin/schema/nexusphp.py
pt_checkin/schema/ocelot.py
pt_checkin/schema/private_torrent.py
pt_checkin/schema/unit3d.py
pt_checkin/schema/xbt.py
pt_checkin/schema/xbtit.py
pt_checkin/schema/xwt.py
pt_checkin/sites/0ff.py
pt_checkin/sites/1ptba.py
pt_checkin/sites/52pt.py
pt_checkin/sites/__init__.py
pt_checkin/sites/abn.py
pt_checkin/sites/abtorrents.py
pt_checkin/sites/aither.py
pt_checkin/sites/audiences.py
pt_checkin/sites/avistaz.py
pt_checkin/sites/azusa.py
pt_checkin/sites/beyond-hd.py
pt_checkin/sites/bitporn.py
pt_checkin/sites/bitsexy.py
pt_checkin/sites/blutopia.py
pt_checkin/sites/bootytape.py
pt_checkin/sites/btschool.py
pt_checkin/sites/byr.py
pt_checkin/sites/carpt.py
pt_checkin/sites/cathode-ray.py
pt_checkin/sites/cinemaz.py
pt_checkin/sites/crabpt.py
pt_checkin/sites/cyanbug.py
pt_checkin/sites/dicmusic.py
pt_checkin/sites/digitalcore.py
pt_checkin/sites/discfan.py
pt_checkin/sites/dmhy.py
pt_checkin/sites/dragonhd.py
pt_checkin/sites/eastgame.py
pt_checkin/sites/empornium.py
pt_checkin/sites/et8.py
pt_checkin/sites/exoticaz.py
pt_checkin/sites/femdomcult.py
pt_checkin/sites/filelist.py
pt_checkin/sites/gay-torrents_net.py
pt_checkin/sites/gay-torrents_org.py
pt_checkin/sites/gaytor.py
pt_checkin/sites/gazellegames.py
pt_checkin/sites/ggpt.py
pt_checkin/sites/greatposterwall.py
pt_checkin/sites/gtk.py
pt_checkin/sites/haidan.py
pt_checkin/sites/happyfappy.py
pt_checkin-0.3.1.dist-info/licenses/LICENSE
pt_checkin-0.3.1.dist-info/METADATA
pt_checkin-0.3.1.dist-info/WHEEL
pt_checkin-0.3.1.dist-info/entry_points.txt
pt_checkin-0.3.1.dist-info/top_level.txt
pt_checkin-0.3.1.dist-info/RECORD
