Metadata-Version: 2.4
Name: pt-checkin
Version: 0.3.1
Summary: PT站点自动签到工具 - 升级版本，支持智能Cloudflare绕过和浏览器模拟
Author: wuyaos
Maintainer: wuyaos
License: MIT
Project-URL: Homepage, https://github.com/wuyaos/pt-checkin
Project-URL: Repository, https://github.com/wuyaos/pt-checkin
Project-URL: Issues, https://github.com/wuyaos/pt-checkin/issues
Project-URL: Documentation, https://github.com/wuyaos/pt-checkin/blob/main/README.md
Keywords: pt,checkin,signin,automation
Classifier: Development Status :: 4 - Beta
Classifier: Intended Audience :: End Users/Desktop
Classifier: License :: OSI Approved :: MIT License
Classifier: Operating System :: OS Independent
Classifier: Programming Language :: Python :: 3
Classifier: Programming Language :: Python :: 3.8
Classifier: Programming Language :: Python :: 3.9
Classifier: Programming Language :: Python :: 3.10
Classifier: Programming Language :: Python :: 3.11
Classifier: Programming Language :: Python :: 3.12
Classifier: Topic :: Internet :: WWW/HTTP
Classifier: Topic :: System :: Archiving
Requires-Python: >=3.8
License-File: LICENSE
Requires-Dist: requests>=2.28.0
Requires-Dist: loguru>=0.6.0
Requires-Dist: pyyaml>=6.0
Requires-Dist: beautifulsoup4>=4.11.0
Requires-Dist: schedule>=1.2.0
Requires-Dist: click>=8.1.0
Requires-Dist: Pillow>=9.0.0
Requires-Dist: fuzzywuzzy>=0.18.0
Requires-Dist: python-levenshtein>=0.12.0
Requires-Dist: chardet>=5.0.0
Requires-Dist: python-dateutil>=2.8.0
Requires-Dist: DrissionPage>=4.0.0
Provides-Extra: dev
Requires-Dist: pytest>=7.0.0; extra == "dev"
Requires-Dist: pytest-cov>=4.0.0; extra == "dev"
Requires-Dist: black>=22.0.0; extra == "dev"
Requires-Dist: isort>=5.10.0; extra == "dev"
Requires-Dist: flake8>=5.0.0; extra == "dev"
Requires-Dist: mypy>=1.0.0; extra == "dev"
Dynamic: license-file
